{
  "$schema": "https://raw.githubusercontent.com/spdx/spdx-spec/v2.2.1/schemas/spdx-schema.json",
  "spdxVersion": "SPDX-2.2",
  "dataLicense": "CC0-1.0",
  "SPDXID": "SPDXRef-DOCUMENT",
  "documentNamespace": "https://spdx.org/spdxdocs/boost-align-x86-windows-1.88.0-e582c779-7540-4a38-ae42-4b0ce743330a",
  "name": "boost-align:x86-windows@1.88.0 5cfc92c20011a8def42484f4cdecb478187c1e3bc718a6fc25d5ae8ea17673ef",
  "creationInfo": {
    "creators": [
      "Tool: vcpkg-2025-04-16-f9b6c6917b23c1ccf16c1a9f015ebabf8f615045"
    ],
    "created": "2025-05-21T02:57:32Z"
  },
  "relationships": [
    {
      "spdxElementId": "SPDXRef-port",
      "relationshipType": "GENERATES",
      "relatedSpdxElement": "SPDXRef-binary"
    },
    {
      "spdxElementId": "SPDXRef-port",
      "relationshipType": "CONTAINS",
      "relatedSpdxElement": "SPDXRef-file-0"
    },
    {
      "spdxElementId": "SPDXRef-port",
      "relationshipType": "CONTAINS",
      "relatedSpdxElement": "SPDXRef-file-1"
    },
    {
      "spdxElementId": "SPDXRef-binary",
      "relationshipType": "GENERATED_FROM",
      "relatedSpdxElement": "SPDXRef-port"
    },
    {
      "spdxElementId": "SPDXRef-file-0",
      "relationshipType": "CONTAINED_BY",
      "relatedSpdxElement": "SPDXRef-port"
    },
    {
      "spdxElementId": "SPDXRef-file-1",
      "relationshipType": "CONTAINED_BY",
      "relatedSpdxElement": "SPDXRef-port"
    },
    {
      "spdxElementId": "SPDXRef-file-1",
      "relationshipType": "DEPENDENCY_MANIFEST_OF",
      "relatedSpdxElement": "SPDXRef-port"
    }
  ],
  "packages": [
    {
      "name": "boost-align",
      "SPDXID": "SPDXRef-port",
      "versionInfo": "1.88.0",
      "downloadLocation": "git+https://github.com/Microsoft/vcpkg@4924c1722bfca24f9700837388bd5d9481695e2b",
      "homepage": "https://www.boost.org/libs/align",
      "licenseConcluded": "BSL-1.0",
      "licenseDeclared": "NOASSERTION",
      "copyrightText": "NOASSERTION",
      "description": "Boost align module",
      "comment": "This is the port (recipe) consumed by vcpkg."
    },
    {
      "name": "boost-align:x86-windows",
      "SPDXID": "SPDXRef-binary",
      "versionInfo": "5cfc92c20011a8def42484f4cdecb478187c1e3bc718a6fc25d5ae8ea17673ef",
      "downloadLocation": "NONE",
      "licenseConcluded": "BSL-1.0",
      "licenseDeclared": "NOASSERTION",
      "copyrightText": "NOASSERTION",
      "comment": "This is a binary package built by vcpkg."
    },
    {
      "SPDXID": "SPDXRef-resource-0",
      "name": "boostorg/align",
      "downloadLocation": "git+https://github.com/boostorg/align@boost-1.88.0",
      "licenseConcluded": "NOASSERTION",
      "licenseDeclared": "NOASSERTION",
      "copyrightText": "NOASSERTION",
      "checksums": [
        {
          "algorithm": "SHA512",
          "checksumValue": "ebe074938ba8eed72c88dc03194ec578ff478a74bfedd5eaf4b57051e8e2b9b2180261b1a6c575b8dab29047e695c679f3f28a853a005bc3936b024188e51368"
        }
      ]
    }
  ],
  "files": [
    {
      "fileName": "./portfile.cmake",
      "SPDXID": "SPDXRef-file-0",
      "checksums": [
        {
          "algorithm": "SHA256",
          "checksumValue": "4b4da3360869b173a2247b346a5073373fe2ed147f64970f19df645649b34bdc"
        }
      ],
      "licenseConcluded": "NOASSERTION",
      "copyrightText": "NOASSERTION"
    },
    {
      "fileName": "./vcpkg.json",
      "SPDXID": "SPDXRef-file-1",
      "checksums": [
        {
          "algorithm": "SHA256",
          "checksumValue": "b1fecc53bd623cba2ca9482507da5310fdd95d21f3a4bd1071806cebad9510c1"
        }
      ],
      "licenseConcluded": "NOASSERTION",
      "copyrightText": "NOASSERTION"
    }
  ]
}
